pprint_tree/__init__.py
pprint_tree/models.py
pprint_tree/pprint_tree_main.py
pprint_tree/helpers/string_helper.py
pprint_tree/helpers/tree_helper.py
pprint_tree-0.0.3.dist-info/METADATA
pprint_tree-0.0.3.dist-info/WHEEL
pprint_tree-0.0.3.dist-info/licenses/LICENSE
pprint_tree-0.0.3.dist-info/RECORD
